matgrab/__init__.py
matgrab/matgrab.py
matgrab-0.1.0.dist-info/LICENSE
matgrab-0.1.0.dist-info/METADATA
matgrab-0.1.0.dist-info/WHEEL
matgrab-0.1.0.dist-info/top_level.txt
matgrab-0.1.0.dist-info/RECORD
