Metadata-Version: 2.1
Name: matgrab
Version: 0.1.0
Summary: search and extract field names or variables from MATLAB .mat files and return a pandas Dataframe
Home-page: https://github.com/Aaronearlerichardson/matgrab
Author: Aaronearlerichardson
Author-email: jakdaxter31@gmail.com
License: UNKNOWN
Project-URL: Bug Tracker, https://github.com/Aaronearlerichardson/matgrab/issues
Platform: UNKNOWN
Classifier: Programming Language :: Python :: 3
Classifier: License :: OSI Approved :: MIT License
Classifier: Operating System :: OS Independent
Requires-Python: >=3.6
